biometrics_tracker/__init__.py
biometrics_tracker/version.py
biometrics_tracker/config/__init__.py
biometrics_tracker/config/createconfig.py
biometrics_tracker/config/json_handler.py
biometrics_tracker/config/logging_config.py
biometrics_tracker/gui/__init__.py
biometrics_tracker/gui/biometrics_tracker.png
biometrics_tracker/gui/tk_gui.py
biometrics_tracker/gui/validators.py
biometrics_tracker/gui/widgets.py
biometrics_tracker/help/add-edit-person.html
biometrics_tracker/help/add-edit-schedules.html
biometrics_tracker/help/entry-edit.html
biometrics_tracker/help/glossary.html
biometrics_tracker/help/import-export.html
biometrics_tracker/help/reports.html
biometrics_tracker/help/scheduling.html
biometrics_tracker/help/start-scheduler.html
biometrics_tracker/help/startup.html
biometrics_tracker/help/user-doc-index.html
biometrics_tracker/help/viewing-upcoming-events.html
biometrics_tracker/help/css/biometrics-tracker.css
biometrics_tracker/help/images/add-datapoint.png
biometrics_tracker/help/images/add-edit-daily-schedule.png
biometrics_tracker/help/images/add-edit-hourly-schedule.png
biometrics_tracker/help/images/add-edit-monthly-schedule.png
biometrics_tracker/help/images/add-edit-schedules.png
biometrics_tracker/help/images/add-edit-weekly-schedule.png
biometrics_tracker/help/images/add-person.png
biometrics_tracker/help/images/blank-numeric-error.png
biometrics_tracker/help/images/checked-box-in-focus.png
biometrics_tracker/help/images/checked-box-out-of-focus.png
biometrics_tracker/help/images/checked-button-in-focus.png
biometrics_tracker/help/images/combo-box-1.png
biometrics_tracker/help/images/combo-box-2.png
biometrics_tracker/help/images/combo-box-3.png
biometrics_tracker/help/images/config-display.png
biometrics_tracker/help/images/date-validation-error.png
biometrics_tracker/help/images/export-1.png
biometrics_tracker/help/images/export-2.1.png
biometrics_tracker/help/images/export-2.2.png
biometrics_tracker/help/images/export-2.3.png
biometrics_tracker-1.2.2.dist-info/AUTHORS
biometrics_tracker-1.2.2.dist-info/LICENSE
biometrics_tracker-1.2.2.dist-info/METADATA
biometrics_tracker-1.2.2.dist-info/WHEEL
biometrics_tracker-1.2.2.dist-info/entry_points.txt
biometrics_tracker-1.2.2.dist-info/top_level.txt
biometrics_tracker-1.2.2.dist-info/RECORD
