Metadata-Version: 2.1
Name: biometrics-tracker
Version: 1.2.2
Summary: This application records and reports biometric measurements (e.g. weight, blood pressure, pulse)
License: The MIT License (MIT)
Keywords: biometrics,health,blood pressure,blood sugar
Classifier: License :: OSI Approved :: MIT License
Classifier: Programming Language :: Python
Classifier: Programming Language :: Python :: 3
Requires-Python: >=3.8
License-File: LICENSE
License-File: AUTHORS
Requires-Dist: ttkbootstrap (>="1.9.0")
Requires-Dist: fpdf2 (>="2.5.7")
Requires-Dist: schedule (>="1.1.0")
Requires-Dist: pytest
